odoo/addons/base_tier_validation/README.rst
odoo/addons/base_tier_validation/__init__.py
odoo/addons/base_tier_validation/__manifest__.py
odoo/addons/base_tier_validation/data/cron_data.xml
odoo/addons/base_tier_validation/data/mail_data.xml
odoo/addons/base_tier_validation/i18n/base_tier_validation.pot
odoo/addons/base_tier_validation/i18n/de.po
odoo/addons/base_tier_validation/i18n/es.po
odoo/addons/base_tier_validation/i18n/es_MX.po
odoo/addons/base_tier_validation/i18n/fr.po
odoo/addons/base_tier_validation/i18n/it.po
odoo/addons/base_tier_validation/i18n/nl.po
odoo/addons/base_tier_validation/i18n/nl_NL.po
odoo/addons/base_tier_validation/i18n/sv.po
odoo/addons/base_tier_validation/i18n/tr.po
odoo/addons/base_tier_validation/i18n/vi_VN.po
odoo/addons/base_tier_validation/i18n/zh_CN.po
odoo/addons/base_tier_validation/migrations/18.0.2.1.0/pre-migration.py
odoo/addons/base_tier_validation/models/__init__.py
odoo/addons/base_tier_validation/models/res_config_settings.py
odoo/addons/base_tier_validation/models/res_users.py
odoo/addons/base_tier_validation/models/tier_definition.py
odoo/addons/base_tier_validation/models/tier_review.py
odoo/addons/base_tier_validation/models/tier_validation.py
odoo/addons/base_tier_validation/models/tier_validation_exception.py
odoo/addons/base_tier_validation/readme/CONFIGURE.md
odoo/addons/base_tier_validation/readme/CONTRIBUTORS.md
odoo/addons/base_tier_validation/readme/CREDITS.md
odoo/addons/base_tier_validation/readme/DESCRIPTION.md
odoo/addons/base_tier_validation/readme/HISTORY.md
odoo/addons/base_tier_validation/readme/ROADMAP.md
odoo/addons/base_tier_validation/security/ir.model.access.csv
odoo/addons/base_tier_validation/security/tier_validation_security.xml
odoo/addons/base_tier_validation/static/description/icon.png
odoo/addons/base_tier_validation/static/description/icon.svg
odoo/addons/base_tier_validation/static/description/index.html
odoo_addon_base_tier_validation-18.0.3.1.2.dist-info/METADATA
odoo_addon_base_tier_validation-18.0.3.1.2.dist-info/WHEEL
odoo_addon_base_tier_validation-18.0.3.1.2.dist-info/top_level.txt
odoo_addon_base_tier_validation-18.0.3.1.2.dist-info/RECORD
