Metadata-Version: 2.1
Name: odoo-addon-base_tier_validation
Version: 18.0.3.1.2
Requires-Python: >=3.10
Requires-Dist: odoo==18.0.*
Summary: Implement a validation process based on tiers.
Home-page: https://github.com/OCA/server-ux
License: AGPL-3
Author: ForgeFlow, Odoo Community Association (OCA)
Author-email: support@odoo-community.org
Classifier: Programming Language :: Python
Classifier: Framework :: Odoo
Classifier: Framework :: Odoo :: 18.0
Classifier: License :: OSI Approved :: GNU Affero General Public License v3
Classifier: Development Status :: 6 - Mature
